{
  "title": "曹刿论战",
  "author": "左丘明",
  "period": "春秋",
  "group": "齐桓公霸业始兴",
  "category": "周文",
  "map": "images/changshao.jpg",
  "background": "齐与鲁是春秋时期的邻国，都在今山东省，齐在东北部，鲁在西南部。公元前697年，齐襄公即位，政令无常，他的弟弟公子小白和公子纠分别逃到莒国和鲁国避难。次年齐襄公为公孙无知所杀。第三年春天，齐人杀死公孙无知，公子小白抢先回到齐国夺得君位。稍后，鲁庄公也亲自领兵护送公子纠回国争夺君位，八月鲁与齐师战于乾时，鲁军大败。齐桓公逼鲁庄公杀死公子纠。鲁庄公十年春天，齐借口鲁国曾帮助公子纠争夺齐国君位，再次兴兵攻鲁，两军战于长勺。这就是文章所记叙的齐鲁长勺之战。\n\n《曹刿论战》是一篇记叙文。此文讲述了曹刿在长勺之战中对此次战争的一番评论，并在战时活用'一鼓作气，再而衰，三而竭'的原理击退强大齐军的史实。文中说明了在战争中如何正确运用战略防御原则——只有'取信于民'，实行'敌疲我打'的正确方针，选择反攻和追击的有利时机，才能以小敌大，以弱胜强。",
  "annotations": [
    {
      "word": "刿",
      "phonetic": "guì",
      "desc": ""
    },
    {
      "word": "靡",
      "phonetic": "mǐ",
      "desc": ""
    }
  ],
  "content": "十年春，齐师伐我。公将战，曹刿请见。其乡人曰：\"肉食者谋之，又何间焉？\"刿曰：\"肉食者鄙，未能远谋。\"乃入见。问：\"何以战？\"公曰：\"衣食所安，弗敢专也，必以分人。\"对曰：\"小惠未遍，民弗从也。\"公曰：\"牺牲玉帛，弗敢加也，必以信。\"对曰：\"小信未孚，神弗福也。\"公曰：\"小大之狱，虽不能察，必以情。\"对曰：\"忠之属也。可以一战。战则请从。\"\n公与之乘，战于长勺。公将鼓之。刿曰：\"未可。\"齐人三鼓。刿曰：\"可矣。\"齐师败绩。公将驰之。刿曰：\"未可。\"下视其辙，登轼而望之，曰：\"可矣。\"遂逐齐师。\n既克，公问其故。对曰：\"夫战，勇气也。一鼓作气，再而衰，三而竭。彼竭我盈，故克之。夫大国，难测也，惧有伏焉。吾视其辙乱，望其旗靡，故逐之。\""
}